SolarEnergyPy/__init__.py
SolarEnergyPy/solarApplication.py
SolarEnergyPy/solarPosFunc.py
SolarEnergyPy/solarPosition.py
SolarEnergyPy/solarRadiation.py
SolarEnergyPy/weatherData.py
SolarEnergyPy-0.0.1.dist-info/LICENSE
SolarEnergyPy-0.0.1.dist-info/METADATA
SolarEnergyPy-0.0.1.dist-info/WHEEL
SolarEnergyPy-0.0.1.dist-info/top_level.txt
SolarEnergyPy-0.0.1.dist-info/RECORD
