Metadata-Version: 2.1
Name: SolarEnergyPy
Version: 0.0.1
Summary: UNKNOWN
Home-page: UNKNOWN
Author: Liqun He
Author-email: heliqun2007@gmail.com
License: MIT
Platform: UNKNOWN
Classifier: Programming Language :: Python :: 3
Classifier: License :: OSI Approved :: MIT License
Classifier: Operating System :: OS Independent
License-File: LICENSE
Requires-Dist: VisualShape3D
Requires-Dist: matplotlib
